TrueFloat/__init__.py
TrueFloat-1.0.2.dist-info/LICENSE
TrueFloat-1.0.2.dist-info/METADATA
TrueFloat-1.0.2.dist-info/WHEEL
TrueFloat-1.0.2.dist-info/top_level.txt
TrueFloat-1.0.2.dist-info/RECORD
