Metadata-Version: 2.1
Name: TrueFloat
Version: 1.0.2
Summary: True float. Without strange num.
Author-email: Furryich <thesavea@gmail.com>
Project-URL: Homepage, https://github.com/UserForBruteer/TrueFloat_py
Project-URL: Issues, https://github.com/UserForBruteer/TrueFloat_py/issues
Classifier: Programming Language :: Python :: 3
Classifier: License :: OSI Approved :: MIT License
Classifier: Operating System :: OS Independent
Requires-Python: >=3.8
License-File: LICENSE
